smart_commit/__init__.py
smart_commit/cli.py
smart_commit/commit.py
smart_commit/utils.py
smart_gcm-0.1.1.dist-info/licenses/LICENSE
smart_gcm-0.1.1.dist-info/METADATA
smart_gcm-0.1.1.dist-info/WHEEL
smart_gcm-0.1.1.dist-info/entry_points.txt
smart_gcm-0.1.1.dist-info/top_level.txt
smart_gcm-0.1.1.dist-info/RECORD
