Metadata-Version: 2.4
Name: smart-gcm
Version: 0.1.1
Summary: AI-powered Git commit message generator using Google Gemini
Home-page: https://github.com/aakashvarma/smart-gcm
Author: Aakash Varma Nadimpalli
Author-email: Your Name <your.email@example.com>
License: MIT
Project-URL: Homepage, https://github.com/aakashvarma/smart-gcm
Project-URL: Bug Reports, https://github.com/aakashvarma/smart-gcm/issues
Project-URL: Source, https://github.com/aakashvarma/smart-gcm
Keywords: git,commit,conventional-commits,ai,gemini
Classifier: Development Status :: 3 - Alpha
Classifier: Intended Audience :: Developers
Classifier: Topic :: Software Development :: Version Control :: Git
Classifier: License :: OSI Approved :: MIT License
Classifier: Programming Language :: Python :: 3
Classifier: Programming Language :: Python :: 3.6
Classifier: Programming Language :: Python :: 3.7
Classifier: Programming Language :: Python :: 3.8
Classifier: Programming Language :: Python :: 3.9
Classifier: Programming Language :: Python :: 3.10
Classifier: Programming Language :: Python :: 3.11
Classifier: Programming Language :: Python :: 3.12
Requires-Python: >=3.6
License-File: LICENSE
Requires-Dist: requests>=2.25.0
Dynamic: author
Dynamic: home-page
Dynamic: license-file
Dynamic: requires-python
